odoo10_addon_l10n_us_form_1099-10.0.1.0.0.99.dev10-py2.7-nspkg.pth
odoo/addons/l10n_us_form_1099/README.rst
odoo/addons/l10n_us_form_1099/__init__.py
odoo/addons/l10n_us_form_1099/__manifest__.py
odoo/addons/l10n_us_form_1099/i18n/l10n_us_form_1099.pot
odoo/addons/l10n_us_form_1099/i18n/nl_NL.po
odoo/addons/l10n_us_form_1099/models/__init__.py
odoo/addons/l10n_us_form_1099/models/res_partner.py
odoo/addons/l10n_us_form_1099/static/description/l10n_us_form_1099.png
odoo/addons/l10n_us_form_1099/static/description/l10n_us_form_1099.svg
odoo/addons/l10n_us_form_1099/views/res_partner.xml
odoo10_addon_l10n_us_form_1099-10.0.1.0.0.99.dev10.dist-info/METADATA
odoo10_addon_l10n_us_form_1099-10.0.1.0.0.99.dev10.dist-info/RECORD
odoo10_addon_l10n_us_form_1099-10.0.1.0.0.99.dev10.dist-info/WHEEL
odoo10_addon_l10n_us_form_1099-10.0.1.0.0.99.dev10.dist-info/namespace_packages.txt
odoo10_addon_l10n_us_form_1099-10.0.1.0.0.99.dev10.dist-info/top_level.txt
